IC/DTC.py
IC/PCA.py
IC/SVD.py
IC/__init__.py
IC/base.py
IC/main.py
witchy/__init__.py
witchy/base.py
witchy/doc.py
witchy/error.py
witchy/magic.py
witchy/media.py
witchy/pic.py
witchy-0.0.2.dist-info/LICENSE
witchy-0.0.2.dist-info/METADATA
witchy-0.0.2.dist-info/WHEEL
witchy-0.0.2.dist-info/top_level.txt
witchy-0.0.2.dist-info/RECORD
