Metadata-Version: 2.1
Name: witchy
Version: 0.0.2
Summary: this is a file tool for python
Home-page: https://github.com/hughie21/witchy
Author: Hughie
Author-email: 18028012455@163.com
License: UNKNOWN
Platform: UNKNOWN
Classifier: Programming Language :: Python :: 3
Classifier: License :: OSI Approved :: MIT License
Classifier: Operating System :: OS Independent
License-File: LICENSE
